{
  "id": "api/hedging-strategy",
  "title": "HedgingStrategy",
  "description": "The HedgingStrategy improves performance by executing multiple parallel attempts and returning the first successful result, reducing latency caused by slow responses.",
  "source": "@site/docs/api/hedging-strategy.md",
  "sourceDirName": "api",
  "slug": "/api/hedging-strategy",
  "permalink": "/polly_dart/docs/api/hedging-strategy",
  "draft": false,
  "unlisted": false,
  "editUrl": "https://github.com/flutterninja9/polly_dart/tree/main/docs/docs/api/hedging-strategy.md",
  "tags": [],
  "version": "current",
  "sidebarPosition": 9,
  "frontMatter": {
    "sidebar_position": 9
  },
  "sidebar": "tutorialSidebar",
  "previous": {
    "title": "FallbackStrategy",
    "permalink": "/polly_dart/docs/api/fallback-strategy"
  },
  "next": {
    "title": "RateLimiterStrategy",
    "permalink": "/polly_dart/docs/api/rate-limiter-strategy"
  }
}